tral/__init__.py
tral/__main__.py
tral/configuration.py
tral/conftest.py
tral/paths.py
tral/examples/example_workflow_MBE2014.py
tral/examples/data/HIV-1_388796.faa
tral/examples/data/HIV-1_388796.pickle
tral/examples/data/Kelch_1.hmm
tral/examples/data/P51610.fasta
tral/examples/data/P51610.fasta.fai
tral/examples/workflow/PRDM_PFAM_models.hmm
tral/examples/workflow/tandem_repeat_annotation_scripts.py
tral/examples/workflow/tandem_repeat_annotation_workflow.ini
tral/examples/workflow/tandem_repeat_annotation_workflow.py
tral/examples/workflow/uniprot_PRDM.fasta
tral/examples/workflow/uniprot_PRDM_annotation.tsv
tral/examples/workflow/split_sequence_data/uniprot_PRDM_1.fasta
tral/examples/workflow/split_sequence_data/uniprot_PRDM_2.fasta
tral/hmm/__init__.py
tral/hmm/hmm.py
tral/hmm/hmm_io.py
tral/hmm/hmm_own_model.py
tral/hmm/hmm_viterbi.py
tral/hmm/test/hmm_io_test.py
tral/hmm/test/hmm_test.py
tral/hmm/test/hmm_viterbi_test.py
tral/repeat/__init__.py
tral/repeat/repeat.py
tral/repeat/repeat_align.py
tral/repeat/repeat_exon.py
tral/repeat/repeat_io.py
tral/repeat/repeat_pvalue.py
tral/repeat/repeat_score.py
tral/repeat/test/repeat_align_test.py
tral/repeat/test/repeat_score_test.py
tral/repeat/test/repeat_test.py
tral/repeat_list/__init__.py
tral/repeat_list/repeat_list.py
tral/repeat_list/repeat_list_io.py
tral/repeat_list/test/repeat_list_io_test.py
tral/repeat_list/test/repeat_list_test.py
tral/search/__init__.py
tral/search/filter_hmm.py
tral/search/search_hmm.py
tral/sequence/__init__.py
tral/sequence/repeat_detection_io.py
tral/sequence/repeat_detection_run.py
tral/sequence/sequence.py
tral/sequence/sequence_io.py
tral/sequence/test/repeat_detection_run_test.py
tral/sequence/test/sequence_io_test.py
tral/sequence/test/sequence_test.py
tral/test/test_workflow.py
tral/tral_configuration/config.ini
tral/tral_configuration/logging.ini
tral/tral_configuration/spec.ini
tral-2.0.data/scripts/example_workflow_MBE2014.py
tral-2.0.dist-info/LICENSE.txt
tral-2.0.dist-info/METADATA
tral-2.0.dist-info/WHEEL
tral-2.0.dist-info/top_level.txt
tral-2.0.dist-info/RECORD
