Metadata-Version: 2.1
Name: tral
Version: 2.0
Summary: Detect and evaluate tandem repeats in genomic sequence data.
Home-page: http://pypi.python.org/pypi/tral/
Author: Elke Schaper
Author-email: elke.schaper@isb-sib.ch
License: LICENSE.txt
Platform: UNKNOWN
Classifier: Intended Audience :: Science/Research
Classifier: Intended Audience :: Developers
Classifier: Programming Language :: Python
Classifier: Programming Language :: Python :: 3
Classifier: Programming Language :: Python :: 3.6
Classifier: Programming Language :: Python :: 3.7
Classifier: Natural Language :: English
Classifier: Topic :: Software Development
Classifier: Topic :: Scientific/Engineering
Classifier: Operating System :: OS Independent
Requires-Dist: biopython (>=1.64)
Requires-Dist: configobj (>=5.0.6)
Requires-Dist: numpy (>=1.6.1)
Requires-Dist: scipy (>=0.12.0)
Provides-Extra: develop
Requires-Dist: flake8-colors ; extra == 'develop'
Requires-Dist: flake8 (>=3.6) ; extra == 'develop'
Requires-Dist: pytest (>=2.5.2) ; extra == 'develop'
Requires-Dist: tox (>=3.5) ; extra == 'develop'
Provides-Extra: docs
Requires-Dist: Sphinx (>=1.2.2) ; extra == 'docs'
Requires-Dist: docutils (>=0.11) ; extra == 'docs'
Requires-Dist: pypandoc (>=0.9.6) ; extra == 'docs'
Provides-Extra: workflow
Requires-Dist: pyfaidx (==0.4.7.1) ; extra == 'workflow'
